edube_module5/__init__.py
edube_module5/iota.py
edube_module5/good/alpha.py
edube_module5/good/beta.py
edube_module5/good/best/sigma.py
edube_module5/good/best/tau.py
edube_module5/ugly/omega.py
edube_module5/ugly/psi.py
edube_module5-1.0.10.dist-info/AUTHORS
edube_module5-1.0.10.dist-info/LICENSE
edube_module5-1.0.10.dist-info/METADATA
edube_module5-1.0.10.dist-info/WHEEL
edube_module5-1.0.10.dist-info/entry_points.txt
edube_module5-1.0.10.dist-info/top_level.txt
edube_module5-1.0.10.dist-info/RECORD
