Metadata-Version: 2.1
Name: edube-module5
Version: 1.0.10
Summary: Smart robots controller 1
Home-page: https://gitlab.com/SamSafonov/edube_module5
Author: Semyon Safonov
Author-email: samsaf@gmail.com
License: BSD 1
Platform: UNKNOWN
